shipyard_googledrive/__init__.py
shipyard_googledrive/cli/authtest.py
shipyard_googledrive/cli/download.py
shipyard_googledrive/cli/upload.py
shipyard_googledrive/drive_utils.py
shipyard_googledrive/googledrive.py
shipyard_googledrive-0.1.4.dist-info/METADATA
shipyard_googledrive-0.1.4.dist-info/WHEEL
shipyard_googledrive-0.1.4.dist-info/RECORD
