Metadata-Version: 2.1
Name: shipyard-googledrive
Version: 0.1.4
Summary: A local client for connecting and working with Google Drive
License: Apache 2.0
Author: wrp801
Author-email: wespoulsen@gmail.com
Requires-Python: >=3.9,<4.0
Classifier: License :: Other/Proprietary License
Classifier: Programming Language :: Python :: 3
Classifier: Programming Language :: Python :: 3.9
Classifier: Programming Language :: Python :: 3.10
Classifier: Programming Language :: Python :: 3.11
Requires-Dist: google-api-python-client (==2.7)
Requires-Dist: google-auth-httplib2 (==0.1.0)
Requires-Dist: shipyard-bp-utils (>=0.1.1,<0.2.0)
Requires-Dist: shipyard-templates (==0.4.2)
